blockplotlib/__init__.py
blockplotlib/blockplotlib.py
blockplotlib-2023.1.4.dist-info/LICENSE
blockplotlib-2023.1.4.dist-info/METADATA
blockplotlib-2023.1.4.dist-info/WHEEL
blockplotlib-2023.1.4.dist-info/top_level.txt
blockplotlib-2023.1.4.dist-info/RECORD
