Metadata-Version: 2.1
Name: blockplotlib
Version: 2023.1.4
Summary: Matplotlib-based library for the creation of block diagrams
Home-page: https://github.com/riemarc/blockplotlib
Author: Marcus Riesmeier
Author-email: gluehen-sierren-0c@icloud.com
License: BSD 3-Clause License
Classifier: Programming Language :: Python :: 3
Classifier: License :: OSI Approved :: BSD License
Classifier: Operating System :: OS Independent
License-File: LICENSE
Requires-Dist: matplotlib
Requires-Dist: Shapely
